flask_wtf_top/__init__.py
flask_wtf_top-2021.11.3.dist-info/LICENSE
flask_wtf_top-2021.11.3.dist-info/METADATA
flask_wtf_top-2021.11.3.dist-info/WHEEL
flask_wtf_top-2021.11.3.dist-info/top_level.txt
flask_wtf_top-2021.11.3.dist-info/RECORD
